nflaunch/__init__.py
nflaunch/__main__.py
nflaunch/backends/base.py
nflaunch/backends/gcp/batch.py
nflaunch/backends/gcp/file.py
nflaunch/backends/gcp/job.py
nflaunch/backends/gcp/templates/gcp.config.template
nflaunch/backends/gcp/templates/gcp.extras.template
nflaunch/cli/formatter.py
nflaunch/cli/main.py
nflaunch/cli/parser.py
nflaunch/cli/validator.py
nflaunch/command/base.py
nflaunch/command/nextflow.py
nflaunch/launcher/nextflow.py
nflaunch/plugins/__init__.py
nflaunch/plugins/base.py
nflaunch/plugins/oncoanalyser/README.md
nflaunch/plugins/oncoanalyser/oncoanalyser.py
nflaunch/utils/logger.py
nflaunch/utils/paths.py
nflaunch/utils/registry.py
nflaunch/utils/templates.py
nflaunch/utils/upload.py
nflaunch-0.1.1.dist-info/licenses/LICENSE
tests/test_dependencies.py
tests/test_gcs_structure.py
nflaunch-0.1.1.dist-info/METADATA
nflaunch-0.1.1.dist-info/WHEEL
nflaunch-0.1.1.dist-info/entry_points.txt
nflaunch-0.1.1.dist-info/top_level.txt
nflaunch-0.1.1.dist-info/RECORD
