Metadata-Version: 2.4
Name: nflaunch
Version: 0.1.1
Summary: Command-line tool to run Nextflow pipelines in the cloud
Author-email: Rodrigo Jara Calogeropulos <r.a.jara@prinsesmaximacentrum.nl>, GenomicsCore at Princess Maxima Center <genomicscore@prinsesmaximacentrum.nl>
License:                                  Apache License
Project-URL: Homepage, https://github.com/rodjc/nflaunch
Project-URL: Documentation, https://github.com/rodjc/nflaunch/blob/main/README.md
Project-URL: Repository, https://github.com/rodjc/nflaunch
Project-URL: Changelog, https://github.com/rodjc/nflaunch/blob/main/CHANGELOG.md
Project-URL: Issues, https://github.com/rodjc/nflaunch/issues
Keywords: nextflow,bioinformatics,cloud,gcp,pipeline,workflow
Classifier: Development Status :: 4 - Beta
Classifier: Intended Audience :: Science/Research
Classifier: License :: OSI Approved :: Apache Software License
Classifier: Operating System :: OS Independent
Classifier: Programming Language :: Python :: 3
Classifier: Programming Language :: Python :: 3.10
Classifier: Programming Language :: Python :: 3.11
Classifier: Programming Language :: Python :: 3.12
Classifier: Topic :: Scientific/Engineering :: Bio-Informatics
Requires-Python: >=3.10
License-File: LICENSE
Requires-Dist: cachetools==5.5.2
Requires-Dist: certifi==2025.7.14
Requires-Dist: charset-normalizer==3.4.2
Requires-Dist: google-api-core==2.25.1
Requires-Dist: google-auth==2.40.3
Requires-Dist: google-cloud-batch==0.17.36
Requires-Dist: google-cloud-core==2.4.3
Requires-Dist: google-cloud-storage==3.2.0
Requires-Dist: google-crc32c==1.7.1
Requires-Dist: google-resumable-media==2.7.2
Requires-Dist: googleapis-common-protos==1.70.0
Requires-Dist: grpcio==1.74.0
Requires-Dist: grpcio-status==1.74.0
Requires-Dist: idna==3.10
Requires-Dist: proto-plus==1.26.1
Requires-Dist: protobuf==6.31.1
Requires-Dist: pyasn1==0.6.1
Requires-Dist: pyasn1-modules==0.4.2
Requires-Dist: requests==2.32.4
Requires-Dist: rsa==4.9.1
Requires-Dist: tomli==2.0.2
Requires-Dist: urllib3==2.5.0
Provides-Extra: dev
Requires-Dist: pytest>=8.0.0; extra == "dev"
Requires-Dist: pytest-cov>=4.1.0; extra == "dev"
Requires-Dist: ruff>=0.3.0; extra == "dev"
Requires-Dist: mypy>=1.8.0; extra == "dev"
Requires-Dist: pre-commit>=3.6.0; extra == "dev"
Dynamic: license-file
